Metadata-Version: 2.4
Name: france-connect-py
Version: 2.1.1
Summary: A Python client to handle communication with FranceConnect
Home-page: https://github.com/Codoc-os/france-connect-py
Author: Codoc
Author-email: support@codoc.co
License: MIT License
Keywords: france-connect france-connect-py
Classifier: Intended Audience :: Developers
Classifier: Natural Language :: English
Classifier: Development Status :: 4 - Beta
Classifier: Programming Language :: Python :: 3
Classifier: Programming Language :: Python :: 3.9
Classifier: Programming Language :: Python :: 3.10
Classifier: Programming Language :: Python :: 3.11
Classifier: Programming Language :: Python :: 3.12
Classifier: Programming Language :: Python :: 3.13
License-File: LICENSE
License-File: AUTHORS.md
Requires-Dist: pyjwt[crypto]<3.0.0,>=2.9.0
Requires-Dist: requests<3.0.0,>=2.32.3
Dynamic: author
Dynamic: author-email
Dynamic: classifier
Dynamic: description
Dynamic: description-content-type
Dynamic: home-page
Dynamic: keywords
Dynamic: license
Dynamic: license-file
Dynamic: requires-dist
Dynamic: summary
